{
  "buffers": [
    {
      "alignment": 4,
      "batch": 0,
      "channel_first": true,
      "channel_last": true,
      "epochs": {
        "end": 1,
        "start": 0
      },
      "flags": "STAI_FLAG_WEIGHTS|STAI_FLAG_CONST|STAI_FLAG_PREALLOCATED",
      "format": "STAI_FORMAT_FLOAT",
      "id": 385,
      "intq": {},
      "is_param": true,
      "mpool_id": 1,
      "name": "conv2d_10_bias_array",
      "nbits": 32,
      "offset_start": 3904,
      "qmn": {},
      "shape": [
        32
      ],
      "shape_map": [
        "CH"
      ],
      "size_bytes": 128
    },
    {
      "alignment": 4,
      "batch": 0,
      "channel_first": false,
      "channel_last": true,
      "epochs": {
        "end": 28,
        "start": 24
      },
      "flags": "STAI_FLAG_PREALLOCATED|STAI_FLAG_ACTIVATIONS",
      "format": "STAI_FORMAT_FLOAT",
      "id": 316,
      "intq": {},
      "is_param": false,
      "mpool_id": 0,
      "name": "conv2d_10_output_array",
      "nbits": 32,
      "offset_start": 13504,
      "qmn": {},
      "shape": [
        5,
        42,
        32
      ],
      "shape_map": [
        "H",
        "W",
        "CH"
      ],
      "size_bytes": 26880
    },
    {
      "alignment": 4,
      "batch": 0,
      "channel_first": false,
      "channel_last": true,
      "epochs": {
        "end": 26,
        "start": 23
      },
      "flags": "STAI_FLAG_PREALLOCATED|STAI_FLAG_ACTIVATIONS|STAI_FLAG_SCRATCHS",
      "format": "STAI_FORMAT_FLOAT",
      "id": 462,
      "intq": {},
      "is_param": false,
      "mpool_id": 0,
      "name": "conv2d_10_scratch0_array",
      "nbits": 32,
      "offset_start": 13440,
      "qmn": {},
      "shape": [
        1,
        1,
        16,
        1
      ],
      "shape_map": [
        "H",
        "W",
        "CH",
        "CH_IN"
      ],
      "size_bytes": 64
    },
    {
      "alignment": 4,
      "batch": 0,
      "channel_first": true,
      "channel_last": false,
      "epochs": {
        "end": 1,
        "start": 0
      },
      "flags": "STAI_FLAG_WEIGHTS|STAI_FLAG_CONST|STAI_FLAG_PREALLOCATED",
      "format": "STAI_FORMAT_FLOAT",
      "id": 382,
      "intq": {},
      "is_param": true,
      "mpool_id": 1,
      "name": "conv2d_10_weights_array",
      "nbits": 32,
      "offset_start": 1856,
      "qmn": {},
      "shape": [
        32,
        1,
        1,
        16
      ],
      "shape_map": [
        "CH",
        "H",
        "W",
        "CH_IN"
      ],
      "size_bytes": 2048
    },
    {
      "alignment": 4,
      "batch": 0,
      "channel_first": true,
      "channel_last": true,
      "epochs": {
        "end": 1,
        "start": 0
      },
      "flags": "STAI_FLAG_WEIGHTS|STAI_FLAG_CONST|STAI_FLAG_PREALLOCATED",
      "format": "STAI_FORMAT_FLOAT",
      "id": 391,
      "intq": {},
      "is_param": true,
      "mpool_id": 1,
      "name": "conv2d_11_bias_array",
      "nbits": 32,
      "offset_start": 5184,
      "qmn": {},
      "shape": [
        32
      ],
      "shape_map": [
        "CH"
      ],
      "size_bytes": 128
    },
    {
      "alignment": 4,
      "batch": 0,
      "channel_first": false,
      "channel_last": true,
      "epochs": {
        "end": 33,
        "start": 29
      },
      "flags": "STAI_FLAG_PREALLOCATED|STAI_FLAG_ACTIVATIONS",
      "format": "STAI_FORMAT_FLOAT",
      "id": 320,
      "intq": {},
      "is_param": false,
      "mpool_id": 0,
      "name": "conv2d_11_output_array",
      "nbits": 32,
      "offset_start": 0,
      "qmn": {},
      "shape": [
        5,
        42,
        32
      ],
      "shape_map": [
        "H",
        "W",
        "CH"
      ],
      "size_bytes": 26880
    },
    {
      "alignment": 4,
      "batch": 0,
      "channel_first": false,
      "channel_last": true,
      "epochs": {
        "end": 1,
        "start": 0
      },
      "flags": "STAI_FLAG_WEIGHTS|STAI_FLAG_CONST|STAI_FLAG_PREALLOCATED",
      "format": "STAI_FORMAT_FLOAT",
      "id": 388,
      "intq": {},
      "is_param": true,
      "mpool_id": 1,
      "name": "conv2d_11_weights_array",
      "nbits": 32,
      "offset_start": 4032,
      "qmn": {},
      "shape": [
        32,
        3,
        3,
        1
      ],
      "shape_map": [
        "CH_IN",
        "H",
        "W",
        "CH"
      ],
      "size_bytes": 1152
    },
    {
      "alignment": 4,
      "batch": 0,
      "channel_first": true,
      "channel_last": true,
      "epochs": {
        "end": 1,
        "start": 0
      },
      "flags": "STAI_FLAG_WEIGHTS|STAI_FLAG_CONST|STAI_FLAG_PREALLOCATED",
      "format": "STAI_FORMAT_FLOAT",
      "id": 397,
      "intq": {},
      "is_param": true,
      "mpool_id": 1,
      "name": "conv2d_12_bias_array",
      "nbits": 32,
      "offset_start": 11456,
      "qmn": {},
      "shape": [
        48
      ],
      "shape_map": [
        "CH"
      ],
      "size_bytes": 192
    },
    {
      "alignment": 4,
      "batch": 0,
      "channel_first": false,
      "channel_last": true,
      "epochs": {
        "end": 36,
        "start": 32
      },
      "flags": "STAI_FLAG_PREALLOCATED|STAI_FLAG_ACTIVATIONS",
      "format": "STAI_FORMAT_FLOAT",
      "id": 322,
      "intq": {},
      "is_param": false,
      "mpool_id": 0,
      "name": "conv2d_12_output_array",
      "nbits": 32,
      "offset_start": 27008,
      "qmn": {},
      "shape": [
        5,
        42,
        48
      ],
      "shape_map": [
        "H",
        "W",
        "CH"
      ],
      "size_bytes": 40320
    },
    {
      "alignment": 4,
      "batch": 0,
      "channel_first": false,
      "channel_last": true,
      "epochs": {
        "end": 34,
        "start": 31
      },
      "flags": "STAI_FLAG_PREALLOCATED|STAI_FLAG_ACTIVATIONS|STAI_FLAG_SCRATCHS",
      "format": "STAI_FORMAT_FLOAT",
      "id": 470,
      "intq": {},
      "is_param": false,
      "mpool_id": 0,
      "name": "conv2d_12_scratch0_array",
      "nbits": 32,
      "offset_start": 26880,
      "qmn": {},
      "shape": [
        1,
        1,
        32,
        1
      ],
      "shape_map": [
        "H",
        "W",
        "CH",
        "CH_IN"
      ],
      "size_bytes": 128
    },
    {
      "alignment": 4,
      "batch": 0,
      "channel_first": true,
      "channel_last": false,
      "epochs": {
        "end": 1,
        "start": 0
      },
      "flags": "STAI_FLAG_WEIGHTS|STAI_FLAG_CONST|STAI_FLAG_PREALLOCATED",
      "format": "STAI_FORMAT_FLOAT",
      "id": 394,
      "intq": {},
      "is_param": true,
      "mpool_id": 1,
      "name": "conv2d_12_weights_array",
      "nbits": 32,
      "offset_start": 5312,
      "qmn": {},
      "shape": [
        48,
        1,
        1,
        32
      ],
      "shape_map": [
        "CH",
        "H",
        "W",
        "CH_IN"
      ],
      "size_bytes": 6144
    },
    {
      "alignment": 4,
      "batch": 0,
      "channel_first": true,
      "channel_last": true,
      "epochs": {
        "end": 1,
        "start": 0
      },
      "flags": "STAI_FLAG_WEIGHTS|STAI_FLAG_CONST|STAI_FLAG_PREALLOCATED",
      "format": "STAI_FORMAT_FLOAT",
      "id": 403,
      "intq": {},
      "is_param": true,
      "mpool_id": 1,
      "name": "conv2d_13_bias_array",
      "nbits": 32,
      "offset_start": 13376,
      "qmn": {},
      "shape": [
        48
      ],
      "shape_map": [
        "CH"
      ],
      "size_bytes": 192
    },
    {
      "alignment": 4,
      "batch": 0,
      "channel_first": false,
      "channel_last": true,
      "epochs": {
        "end": 41,
        "start": 37
      },
      "flags": "STAI_FLAG_PREALLOCATED|STAI_FLAG_ACTIVATIONS",
      "format": "STAI_FORMAT_FLOAT",
      "id": 326,
      "intq": {},
      "is_param": false,
      "mpool_id": 0,
      "name": "conv2d_13_output_array",
      "nbits": 32,
      "offset_start": 0,
      "qmn": {},
      "shape": [
        5,
        42,
        48
      ],
      "shape_map": [
        "H",
        "W",
        "CH"
      ],
      "size_bytes": 40320
    },
    {
      "alignment": 4,
      "batch": 0,
      "channel_first": false,
      "channel_last": true,
      "epochs": {
        "end": 1,
        "start": 0
      },
      "flags": "STAI_FLAG_WEIGHTS|STAI_FLAG_CONST|STAI_FLAG_PREALLOCATED",
      "format": "STAI_FORMAT_FLOAT",
      "id": 400,
      "intq": {},
      "is_param": true,
      "mpool_id": 1,
      "name": "conv2d_13_weights_array",
      "nbits": 32,
      "offset_start": 11648,
      "qmn": {},
      "shape": [
        48,
        3,
        3,
        1
      ],
      "shape_map": [
        "CH_IN",
        "H",
        "W",
        "CH"
      ],
      "size_bytes": 1728
    },
    {
      "alignment": 4,
      "batch": 0,
      "channel_first": true,
      "channel_last": true,
      "epochs": {
        "end": 1,
        "start": 0
      },
      "flags": "STAI_FLAG_WEIGHTS|STAI_FLAG_CONST|STAI_FLAG_PREALLOCATED",
      "format": "STAI_FORMAT_FLOAT",
      "id": 409,
      "intq": {},
      "is_param": true,
      "mpool_id": 1,
      "name": "conv2d_14_bias_array",
      "nbits": 32,
      "offset_start": 25856,
      "qmn": {},
      "shape": [
        64
      ],
      "shape_map": [
        "CH"
      ],
      "size_bytes": 256
    },
    {
      "alignment": 4,
      "batch": 0,
      "channel_first": false,
      "channel_last": true,
      "epochs": {
        "end": 44,
        "start": 40
      },
      "flags": "STAI_FLAG_PREALLOCATED|STAI_FLAG_ACTIVATIONS",
      "format": "STAI_FORMAT_FLOAT",
      "id": 328,
      "intq": {},
      "is_param": false,
      "mpool_id": 0,
      "name": "conv2d_14_output_array",
      "nbits": 32,
      "offset_start": 65296,
      "qmn": {},
      "shape": [
        5,
        42,
        64
      ],
      "shape_map": [
        "H",
        "W",
        "CH"
      ],
      "size_bytes": 53760
    },
    {
      "alignment": 4,
      "batch": 0,
      "channel_first": false,
      "channel_last": true,
      "epochs": {
        "end": 42,
        "start": 39
      },
      "flags": "STAI_FLAG_PREALLOCATED|STAI_FLAG_ACTIVATIONS|STAI_FLAG_SCRATCHS",
      "format": "STAI_FORMAT_FLOAT",
      "id": 478,
      "intq": {},
      "is_param": false,
      "mpool_id": 0,
      "name": "conv2d_14_scratch0_array",
      "nbits": 32,
      "offset_start": 40320,
      "qmn": {},
      "shape": [
        1,
        1,
        48,
        1
      ],
      "shape_map": [
        "H",
        "W",
        "CH",
        "CH_IN"
      ],
      "size_bytes": 192
    },
    {
      "alignment": 4,
      "batch": 0,
      "channel_first": true,
      "channel_last": false,
      "epochs": {
        "end": 1,
        "start": 0
      },
      "flags": "STAI_FLAG_WEIGHTS|STAI_FLAG_CONST|STAI_FLAG_PREALLOCATED",
      "format": "STAI_FORMAT_FLOAT",
      "id": 406,
      "intq": {},
      "is_param": true,
      "mpool_id": 1,
      "name": "conv2d_14_weights_array",
      "nbits": 32,
      "offset_start": 13568,
      "qmn": {},
      "shape": [
        64,
        1,
        1,
        48
      ],
      "shape_map": [
        "CH",
        "H",
        "W",
        "CH_IN"
      ],
      "size_bytes": 12288
    },
    {
      "alignment": 4,
      "batch": 0,
      "channel_first": true,
      "channel_last": true,
      "epochs": {
        "end": 1,
        "start": 0
      },
      "flags": "STAI_FLAG_WEIGHTS|STAI_FLAG_CONST|STAI_FLAG_PREALLOCATED",
      "format": "STAI_FORMAT_FLOAT",
      "id": 361,
      "intq": {},
      "is_param": true,
      "mpool_id": 1,
      "name": "conv2d_4_bias_array",
      "nbits": 32,
      "offset_start": 288,
      "qmn": {},
      "shape": [
        8
      ],
      "shape_map": [
        "CH"
      ],
      "size_bytes": 32
    },
    {
      "alignment": 4,
      "batch": 0,
      "channel_first": false,
      "channel_last": true,
      "epochs": {
        "end": 12,
        "start": 8
      },
      "flags": "STAI_FLAG_PREALLOCATED|STAI_FLAG_ACTIVATIONS",
      "format": "STAI_FORMAT_FLOAT",
      "id": 304,
      "intq": {},
      "is_param": false,
      "mpool_id": 0,
      "name": "conv2d_4_output_array",
      "nbits": 32,
      "offset_start": 2720,
      "qmn": {},
      "shape": [
        20,
        167,
        8
      ],
      "shape_map": [
        "H",
        "W",
        "CH"
      ],
      "size_bytes": 106880
    },
    {
      "alignment": 4,
      "batch": 0,
      "channel_first": false,
      "channel_last": true,
      "epochs": {
        "end": 10,
        "start": 7
      },
      "flags": "STAI_FLAG_PREALLOCATED|STAI_FLAG_ACTIVATIONS|STAI_FLAG_SCRATCHS",
      "format": "STAI_FORMAT_FLOAT",
      "id": 446,
      "intq": {},
      "is_param": false,
      "mpool_id": 0,
      "name": "conv2d_4_scratch0_array",
      "nbits": 32,
      "offset_start": 119020,
      "qmn": {},
      "shape": [
        3,
        3,
        1,
        1
      ],
      "shape_map": [
        "H",
        "W",
        "CH",
        "CH_IN"
      ],
      "size_bytes": 36
    },
    {
      "alignment": 4,
      "batch": 0,
      "channel_first": true,
      "channel_last": false,
      "epochs": {
        "end": 1,
        "start": 0
      },
      "flags": "STAI_FLAG_WEIGHTS|STAI_FLAG_CONST|STAI_FLAG_PREALLOCATED",
      "format": "STAI_FORMAT_FLOAT",
      "id": 358,
      "intq": {},
      "is_param": true,
      "mpool_id": 1,
      "name": "conv2d_4_weights_array",
      "nbits": 32,
      "offset_start": 0,
      "qmn": {},
      "shape": [
        8,
        3,
        3,
        1
      ],
      "shape_map": [
        "CH",
        "H",
        "W",
        "CH_IN"
      ],
      "size_bytes": 288
    },
    {
      "alignment": 4,
      "batch": 0,
      "channel_first": true,
      "channel_last": true,
      "epochs": {
        "end": 1,
        "start": 0
      },
      "flags": "STAI_FLAG_WEIGHTS|STAI_FLAG_CONST|STAI_FLAG_PREALLOCATED",
      "format": "STAI_FORMAT_FLOAT",
      "id": 367,
      "intq": {},
      "is_param": true,
      "mpool_id": 1,
      "name": "conv2d_6_bias_array",
      "nbits": 32,
      "offset_start": 608,
      "qmn": {},
      "shape": [
        8
      ],
      "shape_map": [
        "CH"
      ],
      "size_bytes": 32
    },
    {
      "alignment": 4,
      "batch": 0,
      "channel_first": false,
      "channel_last": true,
      "epochs": {
        "end": 17,
        "start": 13
      },
      "flags": "STAI_FLAG_PREALLOCATED|STAI_FLAG_ACTIVATIONS",
      "format": "STAI_FORMAT_FLOAT",
      "id": 308,
      "intq": {},
      "is_param": false,
      "mpool_id": 0,
      "name": "conv2d_6_output_array",
      "nbits": 32,
      "offset_start": 0,
      "qmn": {},
      "shape": [
        10,
        84,
        8
      ],
      "shape_map": [
        "H",
        "W",
        "CH"
      ],
      "size_bytes": 26880
    },
    {
      "alignment": 4,
      "batch": 0,
      "channel_first": false,
      "channel_last": true,
      "epochs": {
        "end": 1,
        "start": 0
      },
      "flags": "STAI_FLAG_WEIGHTS|STAI_FLAG_CONST|STAI_FLAG_PREALLOCATED",
      "format": "STAI_FORMAT_FLOAT",
      "id": 364,
      "intq": {},
      "is_param": true,
      "mpool_id": 1,
      "name": "conv2d_6_weights_array",
      "nbits": 32,
      "offset_start": 320,
      "qmn": {},
      "shape": [
        8,
        3,
        3,
        1
      ],
      "shape_map": [
        "CH_IN",
        "H",
        "W",
        "CH"
      ],
      "size_bytes": 288
    },
    {
      "alignment": 4,
      "batch": 0,
      "channel_first": true,
      "channel_last": true,
      "epochs": {
        "end": 1,
        "start": 0
      },
      "flags": "STAI_FLAG_WEIGHTS|STAI_FLAG_CONST|STAI_FLAG_PREALLOCATED",
      "format": "STAI_FORMAT_FLOAT",
      "id": 373,
      "intq": {},
      "is_param": true,
      "mpool_id": 1,
      "name": "conv2d_7_bias_array",
      "nbits": 32,
      "offset_start": 1152,
      "qmn": {},
      "shape": [
        16
      ],
      "shape_map": [
        "CH"
      ],
      "size_bytes": 64
    },
    {
      "alignment": 4,
      "batch": 0,
      "channel_first": false,
      "channel_last": true,
      "epochs": {
        "end": 20,
        "start": 16
      },
      "flags": "STAI_FLAG_PREALLOCATED|STAI_FLAG_ACTIVATIONS",
      "format": "STAI_FORMAT_FLOAT",
      "id": 310,
      "intq": {},
      "is_param": false,
      "mpool_id": 0,
      "name": "conv2d_7_output_array",
      "nbits": 32,
      "offset_start": 26912,
      "qmn": {},
      "shape": [
        10,
        84,
        16
      ],
      "shape_map": [
        "H",
        "W",
        "CH"
      ],
      "size_bytes": 53760
    },
    {
      "alignment": 4,
      "batch": 0,
      "channel_first": false,
      "channel_last": true,
      "epochs": {
        "end": 18,
        "start": 15
      },
      "flags": "STAI_FLAG_PREALLOCATED|STAI_FLAG_ACTIVATIONS|STAI_FLAG_SCRATCHS",
      "format": "STAI_FORMAT_FLOAT",
      "id": 454,
      "intq": {},
      "is_param": false,
      "mpool_id": 0,
      "name": "conv2d_7_scratch0_array",
      "nbits": 32,
      "offset_start": 26880,
      "qmn": {},
      "shape": [
        1,
        1,
        8,
        1
      ],
      "shape_map": [
        "H",
        "W",
        "CH",
        "CH_IN"
      ],
      "size_bytes": 32
    },
    {
      "alignment": 4,
      "batch": 0,
      "channel_first": true,
      "channel_last": false,
      "epochs": {
        "end": 1,
        "start": 0
      },
      "flags": "STAI_FLAG_WEIGHTS|STAI_FLAG_CONST|STAI_FLAG_PREALLOCATED",
      "format": "STAI_FORMAT_FLOAT",
      "id": 370,
      "intq": {},
      "is_param": true,
      "mpool_id": 1,
      "name": "conv2d_7_weights_array",
      "nbits": 32,
      "offset_start": 640,
      "qmn": {},
      "shape": [
        16,
        1,
        1,
        8
      ],
      "shape_map": [
        "CH",
        "H",
        "W",
        "CH_IN"
      ],
      "size_bytes": 512
    },
    {
      "alignment": 4,
      "batch": 0,
      "channel_first": true,
      "channel_last": true,
      "epochs": {
        "end": 1,
        "start": 0
      },
      "flags": "STAI_FLAG_WEIGHTS|STAI_FLAG_CONST|STAI_FLAG_PREALLOCATED",
      "format": "STAI_FORMAT_FLOAT",
      "id": 379,
      "intq": {},
      "is_param": true,
      "mpool_id": 1,
      "name": "conv2d_9_bias_array",
      "nbits": 32,
      "offset_start": 1792,
      "qmn": {},
      "shape": [
        16
      ],
      "shape_map": [
        "CH"
      ],
      "size_bytes": 64
    },
    {
      "alignment": 4,
      "batch": 0,
      "channel_first": false,
      "channel_last": true,
      "epochs": {
        "end": 25,
        "start": 21
      },
      "flags": "STAI_FLAG_PREALLOCATED|STAI_FLAG_ACTIVATIONS",
      "format": "STAI_FORMAT_FLOAT",
      "id": 314,
      "intq": {},
      "is_param": false,
      "mpool_id": 0,
      "name": "conv2d_9_output_array",
      "nbits": 32,
      "offset_start": 0,
      "qmn": {},
      "shape": [
        5,
        42,
        16
      ],
      "shape_map": [
        "H",
        "W",
        "CH"
      ],
      "size_bytes": 13440
    },
    {
      "alignment": 4,
      "batch": 0,
      "channel_first": false,
      "channel_last": true,
      "epochs": {
        "end": 1,
        "start": 0
      },
      "flags": "STAI_FLAG_WEIGHTS|STAI_FLAG_CONST|STAI_FLAG_PREALLOCATED",
      "format": "STAI_FORMAT_FLOAT",
      "id": 376,
      "intq": {},
      "is_param": true,
      "mpool_id": 1,
      "name": "conv2d_9_weights_array",
      "nbits": 32,
      "offset_start": 1216,
      "qmn": {},
      "shape": [
        16,
        3,
        3,
        1
      ],
      "shape_map": [
        "CH_IN",
        "H",
        "W",
        "CH"
      ],
      "size_bytes": 576
    },
    {
      "alignment": 4,
      "batch": 0,
      "channel_first": false,
      "channel_last": true,
      "epochs": {
        "end": 62,
        "start": 58
      },
      "flags": "STAI_FLAG_PREALLOCATED|STAI_FLAG_ACTIVATIONS",
      "format": "STAI_FORMAT_FLOAT",
      "id": 346,
      "intq": {},
      "is_param": false,
      "mpool_id": 0,
      "name": "eltwise_24_output_array",
      "nbits": 32,
      "offset_start": 53760,
      "qmn": {},
      "shape": [
        64,
        5,
        42
      ],
      "shape_map": [
        "H",
        "W",
        "CH"
      ],
      "size_bytes": 53760
    },
    {
      "alignment": 4,
      "batch": 0,
      "channel_first": true,
      "channel_last": true,
      "epochs": {
        "end": 1,
        "start": 0
      },
      "flags": "STAI_FLAG_WEIGHTS|STAI_FLAG_CONST|STAI_FLAG_PREALLOCATED",
      "format": "STAI_FORMAT_FLOAT",
      "id": 421,
      "intq": {},
      "is_param": true,
      "mpool_id": 1,
      "name": "gemm_19_bias_array",
      "nbits": 32,
      "offset_start": 28168,
      "qmn": {},
      "shape": [
        8
      ],
      "shape_map": [
        "CH"
      ],
      "size_bytes": 32
    },
    {
      "alignment": 4,
      "batch": 0,
      "channel_first": true,
      "channel_last": true,
      "epochs": {
        "end": 53,
        "start": 50
      },
      "flags": "STAI_FLAG_PREALLOCATED|STAI_FLAG_ACTIVATIONS",
      "format": "STAI_FORMAT_FLOAT",
      "id": 338,
      "intq": {},
      "is_param": false,
      "mpool_id": 0,
      "name": "gemm_19_output_array",
      "nbits": 32,
      "offset_start": 0,
      "qmn": {},
      "shape": [
        8
      ],
      "shape_map": [
        "CH"
      ],
      "size_bytes": 32
    },
    {
      "alignment": 4,
      "batch": 0,
      "channel_first": true,
      "channel_last": true,
      "epochs": {
        "end": 1,
        "start": 0
      },
      "flags": "STAI_FLAG_WEIGHTS|STAI_FLAG_CONST|STAI_FLAG_PREALLOCATED",
      "format": "STAI_FORMAT_FLOAT",
      "id": 418,
      "intq": {},
      "is_param": true,
      "mpool_id": 1,
      "name": "gemm_19_weights_array",
      "nbits": 32,
      "offset_start": 26120,
      "qmn": {},
      "shape": [
        8,
        64
      ],
      "shape_map": [
        "CH",
        "CH_IN"
      ],
      "size_bytes": 2048
    },
    {
      "alignment": 4,
      "batch": 0,
      "channel_first": true,
      "channel_last": true,
      "epochs": {
        "end": 1,
        "start": 0
      },
      "flags": "STAI_FLAG_WEIGHTS|STAI_FLAG_CONST|STAI_FLAG_PREALLOCATED",
      "format": "STAI_FORMAT_FLOAT",
      "id": 427,
      "intq": {},
      "is_param": true,
      "mpool_id": 1,
      "name": "gemm_21_bias_array",
      "nbits": 32,
      "offset_start": 30248,
      "qmn": {},
      "shape": [
        64
      ],
      "shape_map": [
        "CH"
      ],
      "size_bytes": 256
    },
    {
      "alignment": 4,
      "batch": 0,
      "channel_first": true,
      "channel_last": true,
      "epochs": {
        "end": 57,
        "start": 54
      },
      "flags": "STAI_FLAG_PREALLOCATED|STAI_FLAG_ACTIVATIONS",
      "format": "STAI_FORMAT_FLOAT",
      "id": 342,
      "intq": {},
      "is_param": false,
      "mpool_id": 0,
      "name": "gemm_21_output_array",
      "nbits": 32,
      "offset_start": 64,
      "qmn": {},
      "shape": [
        64
      ],
      "shape_map": [
        "CH"
      ],
      "size_bytes": 256
    },
    {
      "alignment": 4,
      "batch": 0,
      "channel_first": true,
      "channel_last": true,
      "epochs": {
        "end": 1,
        "start": 0
      },
      "flags": "STAI_FLAG_WEIGHTS|STAI_FLAG_CONST|STAI_FLAG_PREALLOCATED",
      "format": "STAI_FORMAT_FLOAT",
      "id": 424,
      "intq": {},
      "is_param": true,
      "mpool_id": 1,
      "name": "gemm_21_weights_array",
      "nbits": 32,
      "offset_start": 28200,
      "qmn": {},
      "shape": [
        64,
        8
      ],
      "shape_map": [
        "CH",
        "CH_IN"
      ],
      "size_bytes": 2048
    },
    {
      "alignment": 4,
      "batch": 0,
      "channel_first": true,
      "channel_last": true,
      "epochs": {
        "end": 69,
        "start": 67
      },
      "flags": "STAI_FLAG_OUTPUTS|STAI_FLAG_PREALLOCATED|STAI_FLAG_ACTIVATIONS",
      "format": "STAI_FORMAT_S8",
      "id": 354,
      "intq": {
        "axis": 0,
        "offsets": [
          0
        ],
        "scales": [
          0.0078125
        ]
      },
      "is_param": false,
      "mpool_id": 0,
      "name": "gemm_27_0_conversion_output_array",
      "nbits": 8,
      "offset_start": 8,
      "qmn": {},
      "shape": [
        2
      ],
      "shape_map": [
        "CH"
      ],
      "size_bytes": 2
    },
    {
      "alignment": 4,
      "batch": 0,
      "channel_first": true,
      "channel_last": true,
      "epochs": {
        "end": 1,
        "start": 0
      },
      "flags": "STAI_FLAG_WEIGHTS|STAI_FLAG_CONST|STAI_FLAG_PREALLOCATED",
      "format": "STAI_FORMAT_FLOAT",
      "id": 439,
      "intq": {},
      "is_param": true,
      "mpool_id": 1,
      "name": "gemm_27_bias_array",
      "nbits": 32,
      "offset_start": 31016,
      "qmn": {},
      "shape": [
        2
      ],
      "shape_map": [
        "CH"
      ],
      "size_bytes": 8
    },
    {
      "alignment": 4,
      "batch": 0,
      "channel_first": true,
      "channel_last": true,
      "epochs": {
        "end": 68,
        "start": 65
      },
      "flags": "STAI_FLAG_PREALLOCATED|STAI_FLAG_ACTIVATIONS",
      "format": "STAI_FORMAT_FLOAT",
      "id": 352,
      "intq": {},
      "is_param": false,
      "mpool_id": 0,
      "name": "gemm_27_output_array",
      "nbits": 32,
      "offset_start": 0,
      "qmn": {},
      "shape": [
        2
      ],
      "shape_map": [
        "CH"
      ],
      "size_bytes": 8
    },
    {
      "alignment": 4,
      "batch": 0,
      "channel_first": true,
      "channel_last": true,
      "epochs": {
        "end": 1,
        "start": 0
      },
      "flags": "STAI_FLAG_WEIGHTS|STAI_FLAG_CONST|STAI_FLAG_PREALLOCATED",
      "format": "STAI_FORMAT_FLOAT",
      "id": 436,
      "intq": {},
      "is_param": true,
      "mpool_id": 1,
      "name": "gemm_27_weights_array",
      "nbits": 32,
      "offset_start": 30504,
      "qmn": {},
      "shape": [
        2,
        64
      ],
      "shape_map": [
        "CH",
        "CH_IN"
      ],
      "size_bytes": 512
    },
    {
      "alignment": 4,
      "batch": 0,
      "channel_first": false,
      "channel_last": true,
      "epochs": {
        "end": 4,
        "start": 2
      },
      "flags": "STAI_FLAG_INPUTS|STAI_FLAG_PREALLOCATED|STAI_FLAG_ACTIVATIONS",
      "format": "STAI_FORMAT_S8",
      "id": 298,
      "intq": {
        "axis": 1,
        "offsets": [
          0
        ],
        "scales": [
          0.0078125
        ]
      },
      "is_param": false,
      "mpool_id": 0,
      "name": "input_quantized_input_output_array",
      "nbits": 8,
      "offset_start": 93048,
      "qmn": {},
      "shape": [
        333,
        39
      ],
      "shape_map": [
        "H",
        "CH"
      ],
      "size_bytes": 12987
    },
    {
      "alignment": 4,
      "batch": 0,
      "channel_first": false,
      "channel_last": true,
      "epochs": {
        "end": 30,
        "start": 27
      },
      "flags": "STAI_FLAG_PREALLOCATED|STAI_FLAG_ACTIVATIONS",
      "format": "STAI_FORMAT_FLOAT",
      "id": 318,
      "intq": {},
      "is_param": false,
      "mpool_id": 0,
      "name": "nl_10_nl_output_array",
      "nbits": 32,
      "offset_start": 40384,
      "qmn": {},
      "shape": [
        5,
        42,
        32
      ],
      "shape_map": [
        "H",
        "W",
        "CH"
      ],
      "size_bytes": 26880
    },
    {
      "alignment": 4,
      "batch": 0,
      "channel_first": false,
      "channel_last": true,
      "epochs": {
        "end": 38,
        "start": 35
      },
      "flags": "STAI_FLAG_PREALLOCATED|STAI_FLAG_ACTIVATIONS",
      "format": "STAI_FORMAT_FLOAT",
      "id": 324,
      "intq": {},
      "is_param": false,
      "mpool_id": 0,
      "name": "nl_12_nl_output_array",
      "nbits": 32,
      "offset_start": 67328,
      "qmn": {},
      "shape": [
        5,
        42,
        48
      ],
      "shape_map": [
        "H",
        "W",
        "CH"
      ],
      "size_bytes": 40320
    },
    {
      "alignment": 4,
      "batch": 0,
      "channel_first": false,
      "channel_last": true,
      "epochs": {
        "end": 59,
        "start": 45
      },
      "flags": "STAI_FLAG_PREALLOCATED|STAI_FLAG_ACTIVATIONS",
      "format": "STAI_FORMAT_FLOAT",
      "id": 332,
      "intq": {},
      "is_param": false,
      "mpool_id": 0,
      "name": "nl_16_output_array",
      "nbits": 32,
      "offset_start": 53760,
      "qmn": {},
      "shape": [
        64,
        5,
        42
      ],
      "shape_map": [
        "H",
        "W",
        "CH"
      ],
      "size_bytes": 53760
    },
    {
      "alignment": 4,
      "batch": 0,
      "channel_first": true,
      "channel_last": true,
      "epochs": {
        "end": 55,
        "start": 52
      },
      "flags": "STAI_FLAG_PREALLOCATED|STAI_FLAG_ACTIVATIONS",
      "format": "STAI_FORMAT_FLOAT",
      "id": 340,
      "intq": {},
      "is_param": false,
      "mpool_id": 0,
      "name": "nl_20_output_array",
      "nbits": 32,
      "offset_start": 32,
      "qmn": {},
      "shape": [
        8
      ],
      "shape_map": [
        "CH"
      ],
      "size_bytes": 32
    },
    {
      "alignment": 4,
      "batch": 0,
      "channel_first": true,
      "channel_last": true,
      "epochs": {
        "end": 60,
        "start": 56
      },
      "flags": "STAI_FLAG_PREALLOCATED|STAI_FLAG_ACTIVATIONS",
      "format": "STAI_FORMAT_FLOAT",
      "id": 344,
      "intq": {},
      "is_param": false,
      "mpool_id": 0,
      "name": "nl_22_output_array",
      "nbits": 32,
      "offset_start": 320,
      "qmn": {},
      "shape": [
        64
      ],
      "shape_map": [
        "CH"
      ],
      "size_bytes": 256
    },
    {
      "alignment": 4,
      "batch": 0,
      "channel_first": false,
      "channel_last": true,
      "epochs": {
        "end": 14,
        "start": 11
      },
      "flags": "STAI_FLAG_PREALLOCATED|STAI_FLAG_ACTIVATIONS",
      "format": "STAI_FORMAT_FLOAT",
      "id": 306,
      "intq": {},
      "is_param": false,
      "mpool_id": 0,
      "name": "nl_4_nl_output_array",
      "nbits": 32,
      "offset_start": 2720,
      "qmn": {},
      "shape": [
        20,
        167,
        8
      ],
      "shape_map": [
        "H",
        "W",
        "CH"
      ],
      "size_bytes": 106880
    },
    {
      "alignment": 4,
      "batch": 0,
      "channel_first": false,
      "channel_last": true,
      "epochs": {
        "end": 22,
        "start": 19
      },
      "flags": "STAI_FLAG_PREALLOCATED|STAI_FLAG_ACTIVATIONS",
      "format": "STAI_FORMAT_FLOAT",
      "id": 312,
      "intq": {},
      "is_param": false,
      "mpool_id": 0,
      "name": "nl_7_nl_output_array",
      "nbits": 32,
      "offset_start": 26912,
      "qmn": {},
      "shape": [
        10,
        84,
        16
      ],
      "shape_map": [
        "H",
        "W",
        "CH"
      ],
      "size_bytes": 53760
    },
    {
      "alignment": 4,
      "batch": 0,
      "channel_first": true,
      "channel_last": true,
      "epochs": {
        "end": 1,
        "start": 0
      },
      "flags": "STAI_FLAG_WEIGHTS|STAI_FLAG_CONST|STAI_FLAG_PREALLOCATED",
      "format": "STAI_FORMAT_FLOAT",
      "id": 415,
      "intq": {},
      "is_param": true,
      "mpool_id": 1,
      "name": "reduce_17_Mul_bias_array",
      "nbits": 32,
      "offset_start": 26116,
      "qmn": {},
      "shape": [
        1
      ],
      "shape_map": [
        "CH"
      ],
      "size_bytes": 4
    },
    {
      "alignment": 4,
      "batch": 0,
      "channel_first": false,
      "channel_last": true,
      "epochs": {
        "end": 51,
        "start": 48
      },
      "flags": "STAI_FLAG_PREALLOCATED|STAI_FLAG_ACTIVATIONS",
      "format": "STAI_FORMAT_FLOAT",
      "id": 336,
      "intq": {},
      "is_param": false,
      "mpool_id": 0,
      "name": "reduce_17_Mul_output_array",
      "nbits": 32,
      "offset_start": 256,
      "qmn": {},
      "shape": [
        64,
        1,
        1
      ],
      "shape_map": [
        "H",
        "W",
        "CH"
      ],
      "size_bytes": 256
    },
    {
      "alignment": 4,
      "batch": 0,
      "channel_first": true,
      "channel_last": true,
      "epochs": {
        "end": 1,
        "start": 0
      },
      "flags": "STAI_FLAG_WEIGHTS|STAI_FLAG_CONST|STAI_FLAG_PREALLOCATED",
      "format": "STAI_FORMAT_FLOAT",
      "id": 412,
      "intq": {},
      "is_param": true,
      "mpool_id": 1,
      "name": "reduce_17_Mul_scale_array",
      "nbits": 32,
      "offset_start": 26112,
      "qmn": {},
      "shape": [
        1
      ],
      "shape_map": [
        "CH"
      ],
      "size_bytes": 4
    },
    {
      "alignment": 4,
      "batch": 0,
      "channel_first": false,
      "channel_last": true,
      "epochs": {
        "end": 49,
        "start": 47
      },
      "flags": "STAI_FLAG_PREALLOCATED|STAI_FLAG_ACTIVATIONS",
      "format": "STAI_FORMAT_FLOAT",
      "id": 334,
      "intq": {},
      "is_param": false,
      "mpool_id": 0,
      "name": "reduce_17_output_array",
      "nbits": 32,
      "offset_start": 0,
      "qmn": {},
      "shape": [
        64,
        1,
        1
      ],
      "shape_map": [
        "H",
        "W",
        "CH"
      ],
      "size_bytes": 256
    },
    {
      "alignment": 4,
      "batch": 0,
      "channel_first": false,
      "channel_last": true,
      "epochs": {
        "end": 66,
        "start": 63
      },
      "flags": "STAI_FLAG_PREALLOCATED|STAI_FLAG_ACTIVATIONS",
      "format": "STAI_FORMAT_FLOAT",
      "id": 350,
      "intq": {},
      "is_param": false,
      "mpool_id": 0,
      "name": "reduce_25_Mul_output_array",
      "nbits": 32,
      "offset_start": 256,
      "qmn": {},
      "shape": [
        64,
        1,
        1
      ],
      "shape_map": [
        "H",
        "W",
        "CH"
      ],
      "size_bytes": 256
    },
    {
      "alignment": 4,
      "batch": 0,
      "channel_first": false,
      "channel_last": true,
      "epochs": {
        "end": 64,
        "start": 61
      },
      "flags": "STAI_FLAG_PREALLOCATED|STAI_FLAG_ACTIVATIONS",
      "format": "STAI_FORMAT_FLOAT",
      "id": 348,
      "intq": {},
      "is_param": false,
      "mpool_id": 0,
      "name": "reduce_25_output_array",
      "nbits": 32,
      "offset_start": 0,
      "qmn": {},
      "shape": [
        64,
        1,
        1
      ],
      "shape_map": [
        "H",
        "W",
        "CH"
      ],
      "size_bytes": 256
    },
    {
      "alignment": 4,
      "batch": 0,
      "channel_first": false,
      "channel_last": true,
      "epochs": {
        "end": 9,
        "start": 5
      },
      "flags": "STAI_FLAG_PREALLOCATED|STAI_FLAG_ACTIVATIONS",
      "format": "STAI_FORMAT_FLOAT",
      "id": 302,
      "intq": {},
      "is_param": false,
      "mpool_id": 0,
      "name": "reshape_2_0_conversion_output_array",
      "nbits": 32,
      "offset_start": 67072,
      "qmn": {},
      "shape": [
        39,
        333,
        1
      ],
      "shape_map": [
        "H",
        "W",
        "CH"
      ],
      "size_bytes": 51948
    },
    {
      "alignment": 4,
      "batch": 0,
      "channel_first": false,
      "channel_last": true,
      "epochs": {
        "end": 46,
        "start": 43
      },
      "flags": "STAI_FLAG_PREALLOCATED|STAI_FLAG_ACTIVATIONS",
      "format": "STAI_FORMAT_FLOAT",
      "id": 330,
      "intq": {},
      "is_param": false,
      "mpool_id": 0,
      "name": "transpose_15_output_array",
      "nbits": 32,
      "offset_start": 0,
      "qmn": {},
      "shape": [
        64,
        5,
        42
      ],
      "shape_map": [
        "H",
        "W",
        "CH"
      ],
      "size_bytes": 53760
    },
    {
      "alignment": 4,
      "batch": 0,
      "channel_first": false,
      "channel_last": true,
      "epochs": {
        "end": 6,
        "start": 3
      },
      "flags": "STAI_FLAG_PREALLOCATED|STAI_FLAG_ACTIVATIONS",
      "format": "STAI_FORMAT_S8",
      "id": 300,
      "intq": {
        "axis": 1,
        "offsets": [
          0
        ],
        "scales": [
          0.0078125
        ]
      },
      "is_param": false,
      "mpool_id": 0,
      "name": "transpose_1_output_array",
      "nbits": 8,
      "offset_start": 106036,
      "qmn": {},
      "shape": [
        39,
        333
      ],
      "shape_map": [
        "H",
        "CH"
      ],
      "size_bytes": 12987
    }
  ],
  "environment": {
    "generated_model": {
      "generated_time": "2026-04-08T06:36:40+0700",
      "model_files": [
        {
          "name": "network_1_data_params.h",
          "signature": "0x83ab8c48a51c9879ff2064dc3a50fedd"
        },
        {
          "name": "network_1_data_params.c",
          "signature": "0x4fa3255f952db473f4645dbece9d996f"
        },
        {
          "name": "network_1_data.h",
          "signature": "0x8799f9416dd0acf9fccc4101c6e4c7a0"
        },
        {
          "name": "network_1_data.c",
          "signature": "0x4d3f022b343f8602cf068261440e29c4"
        },
        {
          "name": "network_1_config.h",
          "signature": "0xd5762a2800a95b5b294642f98e2c3bd3"
        },
        {
          "name": "network_1.h",
          "signature": "0x71e80bbccf191a59e5a0960b85e4ad23"
        },
        {
          "name": "network_1.c",
          "signature": "0x20da6244d76a1ac3842345007e9dab3e"
        }
      ],
      "name": "network_1"
    },
    "network_signature": "0x3309547fde5b0772",
    "test_name": "",
    "tools": [
      {
        "arguments": "analyze --target stm32h7 --name network_1 -m D:/Code/AI/EdgeAI/GT/[Ver1]GraduationThesis/light_cnn_0406_135605_final_full_integer_quant.tflite --compression none --verbosity 1 --workspace C:/Users/edoph/AppData/Local/Temp/mxAI_workspace17092316450870014563734277277806439 --output C:/Users/edoph/.stm32cubemx/network_output",
        "environment": [
          "STATS_TYPE=X-CUBE-AI"
        ],
        "input_model": {
          "model_files": [
            {
              "name": "light_cnn_0406_135605_final_full_integer_quant.tflite",
              "signature": "0x91f4a9749e7faab5f80aad6b177cc46b"
            }
          ],
          "n_params": 7754,
          "name": "light_cnn_0406_135605_final_full_integer_quant",
          "size": 8792,
          "type": "tflite"
        },
        "name": "ST.EdgeAI.Core",
        "version": "2.2.0-20266 2adc00962"
      }
    ]
  },
  "graphs": [
    {
      "edges": [
        {
          "buffer": 300,
          "edge_kind": "EDGE_MEMORY",
          "end": {
            "node_id": 33,
            "port": 0
          },
          "id": 0,
          "name": "n32-p0_n33-p0",
          "start": {
            "node_id": 32,
            "port": 0
          }
        },
        {
          "buffer": 302,
          "edge_kind": "EDGE_MEMORY",
          "end": {
            "node_id": 34,
            "port": 0
          },
          "id": 1,
          "name": "n33-p0_n34-p0",
          "start": {
            "node_id": 33,
            "port": 0
          }
        },
        {
          "buffer": 304,
          "edge_kind": "EDGE_MEMORY",
          "end": {
            "node_id": 35,
            "port": 0
          },
          "id": 2,
          "name": "n34-p0_n35-p0",
          "start": {
            "node_id": 34,
            "port": 0
          }
        },
        {
          "buffer": 306,
          "edge_kind": "EDGE_MEMORY",
          "end": {
            "node_id": 36,
            "port": 0
          },
          "id": 3,
          "name": "n35-p0_n36-p0",
          "start": {
            "node_id": 35,
            "port": 0
          }
        },
        {
          "buffer": 308,
          "edge_kind": "EDGE_MEMORY",
          "end": {
            "node_id": 37,
            "port": 0
          },
          "id": 4,
          "name": "n36-p0_n37-p0",
          "start": {
            "node_id": 36,
            "port": 0
          }
        },
        {
          "buffer": 310,
          "edge_kind": "EDGE_MEMORY",
          "end": {
            "node_id": 38,
            "port": 0
          },
          "id": 5,
          "name": "n37-p0_n38-p0",
          "start": {
            "node_id": 37,
            "port": 0
          }
        },
        {
          "buffer": 312,
          "edge_kind": "EDGE_MEMORY",
          "end": {
            "node_id": 39,
            "port": 0
          },
          "id": 6,
          "name": "n38-p0_n39-p0",
          "start": {
            "node_id": 38,
            "port": 0
          }
        },
        {
          "buffer": 314,
          "edge_kind": "EDGE_MEMORY",
          "end": {
            "node_id": 40,
            "port": 0
          },
          "id": 7,
          "name": "n39-p0_n40-p0",
          "start": {
            "node_id": 39,
            "port": 0
          }
        },
        {
          "buffer": 316,
          "edge_kind": "EDGE_MEMORY",
          "end": {
            "node_id": 41,
            "port": 0
          },
          "id": 8,
          "name": "n40-p0_n41-p0",
          "start": {
            "node_id": 40,
            "port": 0
          }
        },
        {
          "buffer": 318,
          "edge_kind": "EDGE_MEMORY",
          "end": {
            "node_id": 42,
            "port": 0
          },
          "id": 9,
          "name": "n41-p0_n42-p0",
          "start": {
            "node_id": 41,
            "port": 0
          }
        },
        {
          "buffer": 320,
          "edge_kind": "EDGE_MEMORY",
          "end": {
            "node_id": 43,
            "port": 0
          },
          "id": 10,
          "name": "n42-p0_n43-p0",
          "start": {
            "node_id": 42,
            "port": 0
          }
        },
        {
          "buffer": 322,
          "edge_kind": "EDGE_MEMORY",
          "end": {
            "node_id": 44,
            "port": 0
          },
          "id": 11,
          "name": "n43-p0_n44-p0",
          "start": {
            "node_id": 43,
            "port": 0
          }
        },
        {
          "buffer": 324,
          "edge_kind": "EDGE_MEMORY",
          "end": {
            "node_id": 45,
            "port": 0
          },
          "id": 12,
          "name": "n44-p0_n45-p0",
          "start": {
            "node_id": 44,
            "port": 0
          }
        },
        {
          "buffer": 326,
          "edge_kind": "EDGE_MEMORY",
          "end": {
            "node_id": 46,
            "port": 0
          },
          "id": 13,
          "name": "n45-p0_n46-p0",
          "start": {
            "node_id": 45,
            "port": 0
          }
        },
        {
          "buffer": 328,
          "edge_kind": "EDGE_MEMORY",
          "end": {
            "node_id": 47,
            "port": 0
          },
          "id": 14,
          "name": "n46-p0_n47-p0",
          "start": {
            "node_id": 46,
            "port": 0
          }
        },
        {
          "buffer": 330,
          "edge_kind": "EDGE_MEMORY",
          "end": {
            "node_id": 48,
            "port": 0
          },
          "id": 15,
          "name": "n47-p0_n48-p0",
          "start": {
            "node_id": 47,
            "port": 0
          }
        },
        {
          "buffer": 332,
          "edge_kind": "EDGE_MEMORY",
          "end": {
            "node_id": 49,
            "port": 0
          },
          "id": 16,
          "name": "n48-p0_n49-p0",
          "start": {
            "node_id": 48,
            "port": 0
          }
        },
        {
          "buffer": 332,
          "edge_kind": "EDGE_MEMORY",
          "end": {
            "node_id": 55,
            "port": 0
          },
          "id": 17,
          "name": "n48-p0_n55-p0",
          "start": {
            "node_id": 48,
            "port": 0
          }
        },
        {
          "buffer": 334,
          "edge_kind": "EDGE_MEMORY",
          "end": {
            "node_id": 50,
            "port": 0
          },
          "id": 18,
          "name": "n49-p0_n50-p0",
          "start": {
            "node_id": 49,
            "port": 0
          }
        },
        {
          "buffer": 336,
          "edge_kind": "EDGE_MEMORY",
          "end": {
            "node_id": 51,
            "port": 0
          },
          "id": 19,
          "name": "n50-p0_n51-p0",
          "start": {
            "node_id": 50,
            "port": 0
          }
        },
        {
          "buffer": 338,
          "edge_kind": "EDGE_MEMORY",
          "end": {
            "node_id": 52,
            "port": 0
          },
          "id": 20,
          "name": "n51-p0_n52-p0",
          "start": {
            "node_id": 51,
            "port": 0
          }
        },
        {
          "buffer": 340,
          "edge_kind": "EDGE_MEMORY",
          "end": {
            "node_id": 53,
            "port": 0
          },
          "id": 21,
          "name": "n52-p0_n53-p0",
          "start": {
            "node_id": 52,
            "port": 0
          }
        },
        {
          "buffer": 342,
          "edge_kind": "EDGE_MEMORY",
          "end": {
            "node_id": 54,
            "port": 0
          },
          "id": 22,
          "name": "n53-p0_n54-p0",
          "start": {
            "node_id": 53,
            "port": 0
          }
        },
        {
          "buffer": 344,
          "edge_kind": "EDGE_MEMORY",
          "end": {
            "node_id": 55,
            "port": 1
          },
          "id": 23,
          "name": "n54-p0_n55-p1",
          "start": {
            "node_id": 54,
            "port": 0
          }
        },
        {
          "buffer": 346,
          "edge_kind": "EDGE_MEMORY",
          "end": {
            "node_id": 56,
            "port": 0
          },
          "id": 24,
          "name": "n55-p0_n56-p0",
          "start": {
            "node_id": 55,
            "port": 0
          }
        },
        {
          "buffer": 348,
          "edge_kind": "EDGE_MEMORY",
          "end": {
            "node_id": 57,
            "port": 0
          },
          "id": 25,
          "name": "n56-p0_n57-p0",
          "start": {
            "node_id": 56,
            "port": 0
          }
        },
        {
          "buffer": 350,
          "edge_kind": "EDGE_MEMORY",
          "end": {
            "node_id": 58,
            "port": 0
          },
          "id": 26,
          "name": "n57-p0_n58-p0",
          "start": {
            "node_id": 57,
            "port": 0
          }
        },
        {
          "buffer": 352,
          "edge_kind": "EDGE_MEMORY",
          "end": {
            "node_id": 59,
            "port": 0
          },
          "id": 27,
          "name": "n58-p0_n59-p0",
          "start": {
            "node_id": 58,
            "port": 0
          }
        }
      ],
      "id": 0,
      "inputs": [
        298
      ],
      "name": "light_cnn_0406_135605_final_full_integer_quant",
      "nodes": [
        {
          "attributes": {
            "c_remapping": "{H: CH, CH: H}",
            "dl_remapping": "[0 2 1]",
            "ir_remapping": "{BATCH: BATCH, H: CH, CH: H}",
            "original_transpose_input": "False",
            "original_transpose_output": "False",
            "transpose_shape_map": "False"
          },
          "description": "Transpose",
          "id": 32,
          "inputs": [
            298
          ],
          "macc": 6493,
          "mapping": "NODE_SW",
          "name": "transpose_1",
          "original_nodes": [
            "1"
          ],
          "outputs": [
            300
          ],
          "scratchs": [],
          "subgraph_nodes": [],
          "sw_functions": [
            "forward_transpose"
          ]
        },
        {
          "attributes": {},
          "description": "Conversion",
          "id": 33,
          "inputs": [
            300
          ],
          "macc": 25974,
          "mapping": "NODE_SW",
          "name": "reshape_2_0_conversion",
          "original_nodes": [
            "2"
          ],
          "outputs": [
            302
          ],
          "scratchs": [],
          "subgraph_nodes": [],
          "sw_functions": [
            "node_convert"
          ]
        },
        {
          "attributes": {
            "dilation": "{H: 1, W: 1}",
            "filter_size": "(3, 3)",
            "groups": "1",
            "is_depthwise": "False",
            "is_grouped_conv": "False",
            "num_filters": "8",
            "pad": "{H: (1, 1), W: (1, 1)}",
            "stride": "(2, 2)",
            "use_bias": "True",
            "weights_prefetch": "True"
          },
          "description": "Conv2D",
          "id": 34,
          "inputs": [
            302,
            358,
            361
          ],
          "macc": 240488,
          "mapping": "NODE_SW",
          "name": "conv2d_4",
          "original_nodes": [
            "3"
          ],
          "outputs": [
            304
          ],
          "scratchs": [
            446
          ],
          "subgraph_nodes": [],
          "sw_functions": [
            "forward_conv2d_if32of32wf32"
          ]
        },
        {
          "attributes": {
            "nonlinearity": "clip",
            "params": "[0.0, 6.0]"
          },
          "description": "Nonlinearity",
          "id": 35,
          "inputs": [
            304
          ],
          "macc": 53440,
          "mapping": "NODE_SW",
          "name": "nl_4_nl",
          "original_nodes": [
            "4"
          ],
          "outputs": [
            306
          ],
          "scratchs": [],
          "subgraph_nodes": [],
          "sw_functions": [
            "forward_clip"
          ]
        },
        {
          "attributes": {
            "dilation": "{H: 1, W: 1}",
            "filter_size": "(3, 3)",
            "groups": "8",
            "is_depthwise": "True",
            "is_grouped_conv": "False",
            "num_filters": "1",
            "pad": "{H: (1, 1), W: (1, 1)}",
            "stride": "(2, 2)",
            "use_bias": "True"
          },
          "description": "Conv2D",
          "id": 36,
          "inputs": [
            306,
            364,
            367
          ],
          "macc": 60488,
          "mapping": "NODE_SW",
          "name": "conv2d_6",
          "original_nodes": [
            "5"
          ],
          "outputs": [
            308
          ],
          "scratchs": [],
          "subgraph_nodes": [],
          "sw_functions": [
            "forward_dw_if32of32wf32"
          ]
        },
        {
          "attributes": {
            "dilation": "{H: 1, W: 1}",
            "filter_size": "(1, 1)",
            "groups": "1",
            "is_depthwise": "False",
            "is_grouped_conv": "False",
            "num_filters": "16",
            "pad": "{H: (0, 0), W: (0, 0)}",
            "stride": "(1, 1)",
            "use_bias": "True",
            "weights_prefetch": "True"
          },
          "description": "Conv2D",
          "id": 37,
          "inputs": [
            308,
            370,
            373
          ],
          "macc": 107536,
          "mapping": "NODE_SW",
          "name": "conv2d_7",
          "original_nodes": [
            "7"
          ],
          "outputs": [
            310
          ],
          "scratchs": [
            454
          ],
          "subgraph_nodes": [],
          "sw_functions": [
            "forward_conv2d_if32of32wf32"
          ]
        },
        {
          "attributes": {
            "nonlinearity": "clip",
            "params": "[0.0, 6.0]"
          },
          "description": "Nonlinearity",
          "id": 38,
          "inputs": [
            310
          ],
          "macc": 26880,
          "mapping": "NODE_SW",
          "name": "nl_7_nl",
          "original_nodes": [
            "7"
          ],
          "outputs": [
            312
          ],
          "scratchs": [],
          "subgraph_nodes": [],
          "sw_functions": [
            "forward_clip"
          ]
        },
        {
          "attributes": {
            "dilation": "{H: 1, W: 1}",
            "filter_size": "(3, 3)",
            "groups": "16",
            "is_depthwise": "True",
            "is_grouped_conv": "False",
            "num_filters": "1",
            "pad": "{H: (1, 1), W: (1, 1)}",
            "stride": "(2, 2)",
            "use_bias": "True"
          },
          "description": "Conv2D",
          "id": 39,
          "inputs": [
            312,
            376,
            379
          ],
          "macc": 30256,
          "mapping": "NODE_SW",
          "name": "conv2d_9",
          "original_nodes": [
            "8"
          ],
          "outputs": [
            314
          ],
          "scratchs": [],
          "subgraph_nodes": [],
          "sw_functions": [
            "forward_dw_if32of32wf32"
          ]
        },
        {
          "attributes": {
            "dilation": "{H: 1, W: 1}",
            "filter_size": "(1, 1)",
            "groups": "1",
            "is_depthwise": "False",
            "is_grouped_conv": "False",
            "num_filters": "32",
            "pad": "{H: (0, 0), W: (0, 0)}",
            "stride": "(1, 1)",
            "use_bias": "True",
            "weights_prefetch": "True"
          },
          "description": "Conv2D",
          "id": 40,
          "inputs": [
            314,
            382,
            385
          ],
          "macc": 107552,
          "mapping": "NODE_SW",
          "name": "conv2d_10",
          "original_nodes": [
            "10"
          ],
          "outputs": [
            316
          ],
          "scratchs": [
            462
          ],
          "subgraph_nodes": [],
          "sw_functions": [
            "forward_conv2d_if32of32wf32"
          ]
        },
        {
          "attributes": {
            "nonlinearity": "clip",
            "params": "[0.0, 6.0]"
          },
          "description": "Nonlinearity",
          "id": 41,
          "inputs": [
            316
          ],
          "macc": 13440,
          "mapping": "NODE_SW",
          "name": "nl_10_nl",
          "original_nodes": [
            "10"
          ],
          "outputs": [
            318
          ],
          "scratchs": [],
          "subgraph_nodes": [],
          "sw_functions": [
            "forward_clip"
          ]
        },
        {
          "attributes": {
            "dilation": "{H: 1, W: 1}",
            "filter_size": "(3, 3)",
            "groups": "32",
            "is_depthwise": "True",
            "is_grouped_conv": "False",
            "num_filters": "1",
            "pad": "{H: (1, 1), W: (1, 1)}",
            "stride": "(1, 1)",
            "use_bias": "True"
          },
          "description": "Conv2D",
          "id": 42,
          "inputs": [
            318,
            388,
            391
          ],
          "macc": 60512,
          "mapping": "NODE_SW",
          "name": "conv2d_11",
          "original_nodes": [
            "11"
          ],
          "outputs": [
            320
          ],
          "scratchs": [],
          "subgraph_nodes": [],
          "sw_functions": [
            "forward_dw_if32of32wf32"
          ]
        },
        {
          "attributes": {
            "dilation": "{H: 1, W: 1}",
            "filter_size": "(1, 1)",
            "groups": "1",
            "is_depthwise": "False",
            "is_grouped_conv": "False",
            "num_filters": "48",
            "pad": "{H: (0, 0), W: (0, 0)}",
            "stride": "(1, 1)",
            "use_bias": "True",
            "weights_prefetch": "True"
          },
          "description": "Conv2D",
          "id": 43,
          "inputs": [
            320,
            394,
            397
          ],
          "macc": 322608,
          "mapping": "NODE_SW",
          "name": "conv2d_12",
          "original_nodes": [
            "12"
          ],
          "outputs": [
            322
          ],
          "scratchs": [
            470
          ],
          "subgraph_nodes": [],
          "sw_functions": [
            "forward_conv2d_if32of32wf32"
          ]
        },
        {
          "attributes": {
            "nonlinearity": "clip",
            "params": "[0.0, 6.0]"
          },
          "description": "Nonlinearity",
          "id": 44,
          "inputs": [
            322
          ],
          "macc": 20160,
          "mapping": "NODE_SW",
          "name": "nl_12_nl",
          "original_nodes": [
            "12"
          ],
          "outputs": [
            324
          ],
          "scratchs": [],
          "subgraph_nodes": [],
          "sw_functions": [
            "forward_clip"
          ]
        },
        {
          "attributes": {
            "dilation": "{H: 1, W: 1}",
            "filter_size": "(3, 3)",
            "groups": "48",
            "is_depthwise": "True",
            "is_grouped_conv": "False",
            "num_filters": "1",
            "pad": "{H: (1, 1), W: (1, 1)}",
            "stride": "(1, 1)",
            "use_bias": "True"
          },
          "description": "Conv2D",
          "id": 45,
          "inputs": [
            324,
            400,
            403
          ],
          "macc": 90768,
          "mapping": "NODE_SW",
          "name": "conv2d_13",
          "original_nodes": [
            "13"
          ],
          "outputs": [
            326
          ],
          "scratchs": [],
          "subgraph_nodes": [],
          "sw_functions": [
            "forward_dw_if32of32wf32"
          ]
        },
        {
          "attributes": {
            "dilation": "{H: 1, W: 1}",
            "filter_size": "(1, 1)",
            "groups": "1",
            "is_depthwise": "False",
            "is_grouped_conv": "False",
            "num_filters": "64",
            "pad": "{H: (0, 0), W: (0, 0)}",
            "stride": "(1, 1)",
            "use_bias": "True",
            "weights_prefetch": "True"
          },
          "description": "Conv2D",
          "id": 46,
          "inputs": [
            326,
            406,
            409
          ],
          "macc": 645184,
          "mapping": "NODE_SW",
          "name": "conv2d_14",
          "original_nodes": [
            "14"
          ],
          "outputs": [
            328
          ],
          "scratchs": [
            478
          ],
          "subgraph_nodes": [],
          "sw_functions": [
            "forward_conv2d_if32of32wf32"
          ]
        },
        {
          "attributes": {
            "c_remapping": "{H: CH, W: H, CH: W}",
            "dl_remapping": "[0 3 1 2]",
            "ir_remapping": "{BATCH: BATCH, H: CH, W: H, CH: W}",
            "original_transpose_input": "False",
            "original_transpose_output": "False",
            "transpose_shape_map": "False"
          },
          "description": "Transpose",
          "id": 47,
          "inputs": [
            328
          ],
          "macc": 6720,
          "mapping": "NODE_SW",
          "name": "transpose_15",
          "original_nodes": [
            "15"
          ],
          "outputs": [
            330
          ],
          "scratchs": [],
          "subgraph_nodes": [],
          "sw_functions": [
            "forward_transpose"
          ]
        },
        {
          "attributes": {
            "nonlinearity": "clip",
            "params": "[0.0, 6.0]"
          },
          "description": "Nonlinearity",
          "id": 48,
          "inputs": [
            330
          ],
          "macc": 26880,
          "mapping": "NODE_SW",
          "name": "nl_16",
          "original_nodes": [
            "16"
          ],
          "outputs": [
            332
          ],
          "scratchs": [],
          "subgraph_nodes": [],
          "sw_functions": [
            "forward_clip"
          ]
        },
        {
          "attributes": {
            "axes": "(W, CH)",
            "keepdims": "True",
            "operation": "sum",
            "orig_axes": "[2, 3]"
          },
          "description": "Reduce",
          "id": 49,
          "inputs": [
            332
          ],
          "macc": 13440,
          "mapping": "NODE_SW",
          "name": "reduce_17",
          "original_nodes": [
            "17"
          ],
          "outputs": [
            334
          ],
          "scratchs": [],
          "subgraph_nodes": [],
          "sw_functions": [
            "forward_reduce"
          ]
        },
        {
          "attributes": {
            "ir_axis": "CH",
            "use_bias": "True"
          },
          "description": "ScaleBias",
          "id": 50,
          "inputs": [
            334,
            412,
            415
          ],
          "macc": 128,
          "mapping": "NODE_SW",
          "name": "reduce_17_Mul",
          "original_nodes": [
            "17"
          ],
          "outputs": [
            336
          ],
          "scratchs": [],
          "subgraph_nodes": [],
          "sw_functions": [
            "forward_bn"
          ]
        },
        {
          "attributes": {
            "num_units": "8",
            "use_bias": "True"
          },
          "description": "Dense",
          "id": 51,
          "inputs": [
            336,
            418,
            421
          ],
          "macc": 520,
          "mapping": "NODE_SW",
          "name": "gemm_19",
          "original_nodes": [
            "19"
          ],
          "outputs": [
            338
          ],
          "scratchs": [],
          "subgraph_nodes": [],
          "sw_functions": [
            "forward_dense"
          ]
        },
        {
          "attributes": {
            "nonlinearity": "relu"
          },
          "description": "Nonlinearity",
          "id": 52,
          "inputs": [
            338
          ],
          "macc": 8,
          "mapping": "NODE_SW",
          "name": "nl_20",
          "original_nodes": [
            "20"
          ],
          "outputs": [
            340
          ],
          "scratchs": [],
          "subgraph_nodes": [],
          "sw_functions": [
            "forward_relu"
          ]
        },
        {
          "attributes": {
            "num_units": "64",
            "use_bias": "True"
          },
          "description": "Dense",
          "id": 53,
          "inputs": [
            340,
            424,
            427
          ],
          "macc": 576,
          "mapping": "NODE_SW",
          "name": "gemm_21",
          "original_nodes": [
            "21"
          ],
          "outputs": [
            342
          ],
          "scratchs": [],
          "subgraph_nodes": [],
          "sw_functions": [
            "forward_dense"
          ]
        },
        {
          "attributes": {
            "nonlinearity": "sigmoid"
          },
          "description": "Nonlinearity",
          "id": 54,
          "inputs": [
            342
          ],
          "macc": 640,
          "mapping": "NODE_SW",
          "name": "nl_22",
          "original_nodes": [
            "22"
          ],
          "outputs": [
            344
          ],
          "scratchs": [],
          "subgraph_nodes": [],
          "sw_functions": [
            "forward_sigmoid"
          ]
        },
        {
          "attributes": {
            "operation": "mul"
          },
          "description": "Eltwise",
          "id": 55,
          "inputs": [
            332,
            344
          ],
          "macc": 13440,
          "mapping": "NODE_SW",
          "name": "eltwise_24",
          "original_nodes": [
            "24"
          ],
          "outputs": [
            346
          ],
          "scratchs": [],
          "subgraph_nodes": [],
          "sw_functions": [
            "forward_eltwise"
          ]
        },
        {
          "attributes": {
            "axes": "(W, CH)",
            "keepdims": "True",
            "operation": "sum",
            "orig_axes": "[2, 3]"
          },
          "description": "Reduce",
          "id": 56,
          "inputs": [
            346
          ],
          "macc": 13440,
          "mapping": "NODE_SW",
          "name": "reduce_25",
          "original_nodes": [
            "25"
          ],
          "outputs": [
            348
          ],
          "scratchs": [],
          "subgraph_nodes": [],
          "sw_functions": [
            "forward_reduce"
          ]
        },
        {
          "attributes": {
            "ir_axis": "CH",
            "use_bias": "True"
          },
          "description": "ScaleBias",
          "id": 57,
          "inputs": [
            348,
            412,
            415
          ],
          "macc": 128,
          "mapping": "NODE_SW",
          "name": "reduce_25_Mul",
          "original_nodes": [
            "25"
          ],
          "outputs": [
            350
          ],
          "scratchs": [],
          "subgraph_nodes": [],
          "sw_functions": [
            "forward_bn"
          ]
        },
        {
          "attributes": {
            "num_units": "2",
            "use_bias": "True"
          },
          "description": "Dense",
          "id": 58,
          "inputs": [
            350,
            436,
            439
          ],
          "macc": 130,
          "mapping": "NODE_SW",
          "name": "gemm_27",
          "original_nodes": [
            "27"
          ],
          "outputs": [
            352
          ],
          "scratchs": [],
          "subgraph_nodes": [],
          "sw_functions": [
            "forward_dense"
          ]
        },
        {
          "attributes": {},
          "description": "Conversion",
          "id": 59,
          "inputs": [
            352
          ],
          "macc": 4,
          "mapping": "NODE_SW",
          "name": "gemm_27_0_conversion",
          "original_nodes": [
            "27"
          ],
          "outputs": [
            354
          ],
          "scratchs": [],
          "subgraph_nodes": [],
          "sw_functions": [
            "node_convert"
          ]
        }
      ],
      "original_inputs": [
        {
          "c_shape_map": [],
          "data_format": {
            "quantizer": "UNIFORM",
            "scale": [
              0.0078125
            ],
            "size": 8,
            "type": "SIGNED",
            "zero": [
              0
            ]
          },
          "name": "input_quantized_input",
          "shape": [
            1,
            333,
            39
          ],
          "shape_map": [
            "BATCH",
            "H",
            "CH"
          ]
        }
      ],
      "original_outputs": [
        {
          "c_shape_map": [],
          "data_format": {
            "quantizer": "UNIFORM",
            "scale": [
              0.0078125
            ],
            "size": 8,
            "type": "SIGNED",
            "zero": [
              0
            ]
          },
          "name": "conversion_28",
          "shape": [
            1,
            2
          ],
          "shape_map": [
            "BATCH",
            "CH"
          ]
        }
      ],
      "outputs": [
        354
      ]
    }
  ],
  "json_schema_version": "2.0",
  "memory_footprint": {
    "activations": 119056,
    "io": [
      0,
      0
    ],
    "kernel_flash": 26863,
    "kernel_ram": 8540,
    "series": "stm32h7",
    "toolchain": "arm-none-eabi-gcc (GNU Tools for STM32 12.3.rel1.20240926-1715) 12.3.1 20230626",
    "toolchain_flash": 1758,
    "toolchain_ram": 0,
    "weights": 31024
  },
  "memory_pools": [
    {
      "address": "NULL",
      "alignment": 4,
      "attributes": {
        "latency": "HIGH",
        "score": 768,
        "throughput": "LOW"
      },
      "buffers": [
        298,
        300,
        302,
        304,
        306,
        308,
        310,
        312,
        314,
        316,
        318,
        320,
        322,
        324,
        326,
        328,
        330,
        332,
        334,
        336,
        338,
        340,
        342,
        344,
        346,
        348,
        350,
        352,
        354,
        446,
        454,
        462,
        470,
        478
      ],
      "id": 0,
      "name": "heap_overlay_pool",
      "offset_start": 0,
      "persistent": false,
      "rights": "ACC_WRITE",
      "size_bytes": -1,
      "subpools": [],
      "used_size_bytes": 119056,
      "user_allocated": false,
      "virtual": false
    },
    {
      "address": "s_network_1_weights_array_u64",
      "alignment": 0,
      "attributes": {
        "latency": "UNDEF",
        "score": 0,
        "throughput": "UNDEF"
      },
      "buffers": [
        358,
        361,
        364,
        367,
        370,
        373,
        376,
        379,
        382,
        385,
        388,
        391,
        394,
        397,
        400,
        403,
        406,
        409,
        412,
        415,
        418,
        421,
        424,
        427,
        436,
        439
      ],
      "id": 1,
      "name": "weights_array",
      "offset_start": 0,
      "persistent": true,
      "rights": "ACC_READ",
      "size_bytes": -1,
      "subpools": [],
      "used_size_bytes": 31024,
      "user_allocated": false,
      "virtual": false
    }
  ]
}